{
    "USER_NOTES": "Provenance and results",
    "json_structure": [
        "model",
        "reference",
        "rip",
        "region",
        "statistic",
        "season"
    ],
    "provenance": {
        "openGL": {
            "shading language version": "1.30",
            "GLX": {
                "client": {
                    "version": "1.4",
                    "vendor": "Mesa Project and SGI"
                },
                "version": "1.4",
                "server": {
                    "version": "1.4",
                    "vendor": "SGI"
                }
            },
            "version": "2.1 Mesa 11.0.7",
            "vendor": "VMware, Inc.",
            "renderer": "Gallium 0.4 on llvmpipe (LLVM 3.6, 128 bits)"
        },
        "userId": "gleckler1",
        "commandLine": "/export_backup/gleckler1/anaconda3/envs/pmpn_0718/bin/mean_climate_driver.py -p /tmp/tmpNMMy_r.py",
        "osAccess": false,
        "platform": {
            "Version": "2.6.32-754.14.2.el6.x86_64",
            "OS": "Linux",
            "Name": "crunchy.llnl.gov"
        },
        "conda": {
            "buildVersion": "3.18.8",
            "Platform": "linux-64",
            "Version": "4.7.5",
            "PythonVersion": "3.7.3.final.0"
        },
        "date": "2019-07-24 09:54:41",
        "packages": {
            "mesalib": null,
            "clapack": null,
            "cdutil": "8.1",
            "lapack": "3.8.0",
            "cdms": "3.1.3",
            "vtk": "8.2.0.1916.8.0.2019.04.29.09.55.g5e9164e3da",
            "esmpy": "7.1.0",
            "matplotlib": "2.2.4",
            "genutil": "8.1.2019.03.15.17.57.gd2395cd.npy1.14",
            "python": "2.7.15",
            "scipy": null,
            "cdtime": "3.1.2.2019.02.09.12.03.gba9e0cb",
            "vcs": "8.1.2019.07.11.14.20.gff404143",
            "esmf": "7.1.0",
            "cdat_info": "8.1.1",
            "PMP": "v1.2-66-g0ac0e39",
            "PMPObs": "See 'References' key below, for detailed obs provenance information.",
            "numpy": "1.16.4",
            "uvcdat": null,
            "blas": "0.3.6",
            "cdp": "1.4.2"
        },
        "history": ""
    },
    "RESULTS": {
        "GFDL-ESM2M": {
            "SimulationDescription": {
                "ModellingGroup": "NOAA GFDL",
                "ModelFreeSpace": "N/A",
                "MIPTable": "Amon",
                "creation_date": "2011-07-13T22:29:16Z",
                "ModelActivity": "CMIP5",
                "Experiment": "historical",
                "tracking_id": "6be3f57f-43a0-4eda-b036-e4a17559e66a",
                "Realization": "r1i1p1",
                "Model": "GFDL-ESM2M"
            },
            "default": {
                "source": "ERA-INT",
                "r1i1p1": {
                    "TROPICS": {
                        "mean-obs_xy": {
                            "ann": "219.692",
                            "djf": "219.708",
                            "mam": "219.728",
                            "jja": "219.871",
                            "son": "219.462"
                        },
                        "rmsc_xy": {
                            "ann": "0.558",
                            "djf": "0.546",
                            "mam": "0.752",
                            "jja": "0.830",
                            "son": "0.597"
                        },
                        "rms_xy": {
                            "ann": "0.998",
                            "djf": "1.337",
                            "mam": "1.071",
                            "jja": "0.998",
                            "son": "0.978"
                        },
                        "std-obs_xy_devzm": {
                            "ann": "0.922"
                        },
                        "mean_xy": {
                            "ann": "218.864",
                            "djf": "218.487",
                            "mam": "218.966",
                            "jja": "219.317",
                            "son": "218.687"
                        },
                        "std_xy_devzm": {
                            "ann": "0.645"
                        },
                        "std-obs_xyt": {
                            "ann": "1.280"
                        },
                        "cor_xy": {
                            "ann": "0.837",
                            "djf": "0.87",
                            "mam": "0.80",
                            "jja": "0.84",
                            "son": "0.78"
                        },
                        "std_xy": {
                            "ann": "0.681",
                            "djf": "0.944",
                            "mam": "0.698",
                            "jja": "1.077",
                            "son": "0.805"
                        },
                        "rms_xyt": {
                            "ann": "1.171"
                        },
                        "rms_devzm": {
                            "ann": "0.494"
                        },
                        "std_xyt": {
                            "ann": "1.061"
                        },
                        "rms_y": {
                            "ann": "0.860"
                        },
                        "std-obs_xy": {
                            "ann": "0.985",
                            "djf": "1.102",
                            "mam": "1.177",
                            "jja": "1.483",
                            "son": "0.955"
                        },
                        "bias_xy": {
                            "ann": "-0.828",
                            "djf": "-1.221",
                            "mam": "-0.762",
                            "jja": "-0.555",
                            "son": "-0.775"
                        },
                        "mae_xy": {
                            "ann": "0.870",
                            "djf": "1.245",
                            "mam": "0.919",
                            "jja": "0.777",
                            "son": "0.842"
                        }
                    },
                    "global": {
                        "mean-obs_xy": {
                            "ann": "218.806",
                            "son": "218.251",
                            "mam": "218.989",
                            "jja": "218.722",
                            "djf": "219.260"
                        },
                        "rmsc_xy": {
                            "ann": "1.544",
                            "son": "1.517",
                            "mam": "2.083",
                            "jja": "1.243",
                            "djf": "2.246"
                        },
                        "rms_xy": {
                            "ann": "1.879",
                            "son": "1.843",
                            "mam": "2.306",
                            "jja": "1.663",
                            "djf": "2.520"
                        },
                        "std-obs_xy_devzm": {
                            "ann": "1.243"
                        },
                        "mean_xy": {
                            "ann": "217.736",
                            "son": "217.204",
                            "mam": "218.001",
                            "jja": "217.616",
                            "djf": "218.118"
                        },
                        "std_xy_devzm": {
                            "ann": "0.909"
                        },
                        "std-obs_xyt": {
                            "ann": "3.764"
                        },
                        "cor_xy": {
                            "ann": "0.832",
                            "son": "0.92",
                            "mam": "0.51",
                            "jja": "0.97",
                            "djf": "0.67"
                        },
                        "std_xy": {
                            "ann": "2.742",
                            "son": "3.818",
                            "mam": "2.164",
                            "jja": "5.107",
                            "djf": "2.014"
                        },
                        "rms_xyt": {
                            "ann": "2.193"
                        },
                        "rms_devzm": {
                            "ann": "0.580"
                        },
                        "std_xyt": {
                            "ann": "3.711"
                        },
                        "rms_y": {
                            "ann": "2.296"
                        },
                        "std-obs_xy": {
                            "ann": "2.018",
                            "son": "3.379",
                            "mam": "2.025",
                            "jja": "4.898",
                            "djf": "3.011"
                        },
                        "bias_xy": {
                            "ann": "-1.070",
                            "son": "-1.047",
                            "mam": "-0.988",
                            "jja": "-1.106",
                            "djf": "-1.142"
                        },
                        "mae_xy": {
                            "ann": "1.340",
                            "son": "1.298",
                            "mam": "1.518",
                            "jja": "1.281",
                            "djf": "1.845"
                        }
                    },
                    "NHEX": {
                        "mean-obs_xy": {
                            "ann": "218.987",
                            "djf": "216.683",
                            "mam": "218.461",
                            "jja": "222.098",
                            "son": "218.720"
                        },
                        "rmsc_xy": {
                            "ann": "1.190",
                            "djf": "1.771",
                            "mam": "1.376",
                            "jja": "1.258",
                            "son": "1.093"
                        },
                        "rms_xy": {
                            "ann": "1.190",
                            "djf": "2.073",
                            "mam": "1.441",
                            "jja": "1.933",
                            "son": "1.097"
                        },
                        "std-obs_xy_devzm": {
                            "ann": "1.804"
                        },
                        "mean_xy": {
                            "ann": "218.976",
                            "djf": "217.761",
                            "mam": "218.889",
                            "jja": "220.631",
                            "son": "218.628"
                        },
                        "std_xy_devzm": {
                            "ann": "1.369"
                        },
                        "std-obs_xyt": {
                            "ann": "3.932"
                        },
                        "cor_xy": {
                            "ann": "0.829",
                            "djf": "0.88",
                            "mam": "0.88",
                            "jja": "0.96",
                            "son": "0.86"
                        },
                        "std_xy": {
                            "ann": "1.638",
                            "djf": "3.571",
                            "mam": "2.024",
                            "jja": "2.694",
                            "son": "1.780"
                        },
                        "rms_xyt": {
                            "ann": "1.858"
                        },
                        "rms_devzm": {
                            "ann": "0.755"
                        },
                        "std_xyt": {
                            "ann": "3.070"
                        },
                        "rms_y": {
                            "ann": "1.305"
                        },
                        "std-obs_xy": {
                            "ann": "2.117",
                            "djf": "3.576",
                            "mam": "2.748",
                            "jja": "3.558",
                            "son": "2.149"
                        },
                        "bias_xy": {
                            "ann": "-0.011",
                            "djf": "1.078",
                            "mam": "0.427",
                            "jja": "-1.467",
                            "son": "-0.092"
                        },
                        "mae_xy": {
                            "ann": "0.961",
                            "djf": "1.655",
                            "mam": "1.233",
                            "jja": "1.601",
                            "son": "0.891"
                        }
                    },
                    "SHEX": {
                        "mean-obs_xy": {
                            "ann": "216.853",
                            "son": "215.359",
                            "mam": "218.037",
                            "jja": "213.046",
                            "djf": "220.940"
                        },
                        "rmsc_xy": {
                            "ann": "1.970",
                            "son": "1.996",
                            "mam": "2.958",
                            "jja": "1.390",
                            "djf": "2.694"
                        },
                        "rms_xy": {
                            "ann": "3.272",
                            "son": "3.236",
                            "mam": "4.110",
                            "jja": "2.311",
                            "djf": "4.186"
                        },
                        "std-obs_xy_devzm": {
                            "ann": "1.105"
                        },
                        "mean_xy": {
                            "ann": "214.240",
                            "son": "212.812",
                            "mam": "215.183",
                            "jja": "211.200",
                            "djf": "217.736"
                        },
                        "std_xy_devzm": {
                            "ann": "0.776"
                        },
                        "std-obs_xyt": {
                            "ann": "5.702"
                        },
                        "cor_xy": {
                            "ann": "0.798",
                            "son": "0.93",
                            "mam": "-0.27",
                            "jja": "0.98",
                            "djf": "0.71"
                        },
                        "std_xy": {
                            "ann": "3.187",
                            "son": "5.303",
                            "mam": "1.754",
                            "jja": "6.223",
                            "djf": "1.067"
                        },
                        "rms_xyt": {
                            "ann": "3.611"
                        },
                        "rms_devzm": {
                            "ann": "0.537"
                        },
                        "std_xyt": {
                            "ann": "5.206"
                        },
                        "rms_y": {
                            "ann": "3.582"
                        },
                        "std-obs_xy": {
                            "ann": "2.110",
                            "son": "5.264",
                            "mam": "1.951",
                            "jja": "5.713",
                            "djf": "3.344"
                        },
                        "bias_xy": {
                            "ann": "-2.613",
                            "son": "-2.546",
                            "mam": "-2.854",
                            "jja": "-1.846",
                            "djf": "-3.204"
                        },
                        "mae_xy": {
                            "ann": "2.659",
                            "son": "2.616",
                            "mam": "3.002",
                            "jja": "1.968",
                            "djf": "3.234"
                        }
                    }
                }
            },
            "InputRegionMD5": null,
            "InputClimatologyFileName": "CMIP5.historical.GFDL-ESM2M.r1i1p1.mon.ta.198101-200512.AC.v20190503.nc",
            "units": "K",
            "InputClimatologyMD5": "2ba00558960849e3c541edc65d4295b6",
            "InputRegionFileName": null
        }
    },
    "METRICS": {
        "rms_xy": {
            "Abstract": "Compute Spatial Root Mean Square",
            "Contact": "pcmdi-metrics@llnl.gov",
            "Name": "Spatial Root Mean Square",
            "URI": "http://uvcdat.llnl.gov/documentation/utilities/utilities-2.html"
        },
        "rmsc_xy": {
            "Abstract": "Compute Centered Spatial Root Mean Square",
            "Contact": "pcmdi-metrics@llnl.gov",
            "Name": "Spatial Root Mean Square",
            "URI": "http://uvcdat.llnl.gov/documentation/utilities/utilities-2.html"
        },
        "std_xy": {
            "Abstract": "Compute Spatial Standard Deviation",
            "Contact": "pcmdi-metrics@llnl.gov",
            "Name": "Spatial Standard Deviation",
            "URI": "http://uvcdat.llnl.gov/documentation/utilities/utilities-2.html"
        },
        "mean_xy": {
            "Abstract": "Area Mean (area weighted)",
            "Contact": "pcmdi-metrics@llnl.gov",
            "Name": "Mean"
        },
        "bias_xy": {
            "Abstract": "Compute Full Average of Model - Observation",
            "Contact": "pcmdi-metrics@llnl.gov",
            "Name": "Bias"
        },
        "cor_xy": {
            "Abstract": "Compute Spatial Correlation",
            "Contact": "pcmdi-metrics@llnl.gov",
            "Name": "Spatial Correlation",
            "URI": "http://uvcdat.llnl.gov/documentation/utilities/utilities-2.html"
        },
        "seasonal_mean": {
            "Abstract": "Compute Seasonal Mean",
            "Contact": "pcmdi-metrics@llnl.gov",
            "Name": "Seasonal Mean",
            "Comments": "Assumes input are 12 months climatology"
        },
        "rms_xyt": {
            "Abstract": "Compute Spatial and Temporal Root Mean Square",
            "Contact": "pcmdi-metrics@llnl.gov",
            "Name": "Spatio-Temporal Root Mean Square",
            "URI": "http://uvcdat.llnl.gov/documentation/utilities/utilities-2.html"
        },
        "std_xyt": {
            "Abstract": "Compute Space-Time Standard Deviation",
            "Contact": "pcmdi-metrics@llnl.gov",
            "Name": "Spatial-temporal Standard Deviation",
            "URI": "http://uvcdat.llnl.gov/documentation/utilities/utilities-2.html"
        },
        "annual_mean": {
            "Abstract": "Compute Annual Mean",
            "Contact": "pcmdi-metrics@llnl.gov",
            "Name": "Annual Mean",
            "Comments": "Assumes input are 12 months climatology",
            "URI": "http://uvcdat.llnl.gov/documentation/utilities/utilities-2.html"
        },
        "zonal_mean": {
            "Abstract": "Compute Zonal Mean",
            "Contact": "pcmdi-metrics@llnl.gov",
            "Name": "Zonal Mean",
            "Comments": "",
            "URI": "http://uvcdat.llnl.gov/documentation/utilities/utilities-2.html"
        },
        "mae_xy": {
            "Abstract": "Compute Full Average of Absolute Difference Between Model And Observation",
            "Contact": "pcmdi-metrics@llnl.gov",
            "Name": "Mean Absolute Error"
        }
    },
    "yaml": "name: pmpn_0718\nchannels:\n  - pcmdi/label/nightly\n  - cdat/label/nightly\n  - conda-forge\n  - defaults\ndependencies:\n  - _libgcc_mutex=0.1=main\n  - asn1crypto=0.24.0=py27_1003\n  - attrs=19.1.0=py_0\n  - backports=1.0=py_2\n  - backports.functools_lru_cache=1.5=py_1\n  - backports_abc=0.5=py_1\n  - bokeh=1.2.0=py27_0\n  - bzip2=1.0.8=h516909a_0\n  - ca-certificates=2019.6.16=hecc5488_0\n  - cdat_info=8.1.1=py_0\n  - cdp=1.4.2=py_1\n  - cdtime=3.1.2.2019.02.09.12.03.gba9e0cb=py27ha5dfbcb_0\n  - cdutil=8.1=py_1\n  - certifi=2019.6.16=py27_1\n  - cffi=1.12.3=py27h8022711_0\n  - chardet=3.0.4=py27_1003\n  - cia=0.0.6=0\n  - click=7.0=py_0\n  - cloudpickle=1.2.1=py_0\n  - cryptography=2.7=py27h72c5cf5_0\n  - curl=7.65.2=hf8cf82a_0\n  - cycler=0.10.0=py_1\n  - cytoolz=0.10.0=py27h516909a_0\n  - dask=1.2.2=py_3\n  - dask-core=1.2.2=py_0\n  - dbus=1.13.6=he372182_0\n  - decorator=4.4.0=py_0\n  - distarray=2.12.2=py_1\n  - distributed=1.28.1=py27_0\n  - dv3d=8.0.2019.02.27.00.48.g5714b60=py_0\n  - enum34=1.1.6=py27_1001\n  - esmf=7.1.0=h9a7cb89_1006\n  - esmpy=7.1.0=py27h24bf2e0_3\n  - expat=2.2.5=he1b5a44_1003\n  - ffmpeg=4.1.3=h167e202_0\n  - fontconfig=2.13.1=he4413a7_1000\n  - freetype=2.10.0=he983fc9_0\n  - functools32=3.2.3.2=py_3\n  - future=0.17.1=py27_1000\n  - futures=3.3.0=py27_0\n  - g2clib=1.6.0=hf3f1b0b_9\n  - genutil=8.1.2019.03.15.17.57.gd2395cd.npy1.14=py27hb3ffb1f_0\n  - gettext=0.19.8.1=hc5be6a0_1002\n  - ghostscript=9.22=hf484d3e_1001\n  - glib=2.58.3=h6f030ca_1002\n  - gmp=6.1.2=hf484d3e_1000\n  - gnutls=3.6.5=hd3a4fd2_1002\n  - gst-plugins-base=1.14.5=h0935bb2_0\n  - gstreamer=1.14.5=h36ae1b5_0\n  - hdf4=4.2.13=h9a582f1_1002\n  - hdf5=1.10.5=nompi_h3c11f04_1100\n  - heapdict=1.0.0=py27_1000\n  - icu=58.2=hf484d3e_1000\n  - idna=2.8=py27_1000\n  - ipaddress=1.0.22=py_1\n  - ipython_genutils=0.2.0=py_1\n  - jasper=1.900.1=h07fcdf6_1006\n  - jinja2=2.10.1=py_0\n  - jpeg=9c=h14c3975_1001\n  - jsonschema=3.0.1=py27_0\n  - jupyter_core=4.4.0=py_0\n  - kiwisolver=1.1.0=py27hc9558a2_0\n  - krb5=1.16.3=h05b26f9_1001\n  - lame=3.100=h14c3975_1001\n  - lazy-object-proxy=1.4.1=py27h516909a_0\n  - libblas=3.8.0=10_openblas\n  - libcblas=3.8.0=10_openblas\n  - libcdms=3.1.2.2019.02.09.03.57.g8f1cefe=h9ac9557_0\n  - libcf=3.1.0.2019.07.05.23.12.g01a0c63=py27h14c3975_0\n  - libcurl=7.65.2=hda55be3_0\n  - libdrs=3.1.2.2019.02.09.01.20.g0c04b0c=h9ac9557_0\n  - libdrs_f=3.1.2.2019.02.09.01.20.g0c04b0c=h9ac9557_0\n  - libedit=3.1.20170329=hf8c457e_1001\n  - libffi=3.2.1=he1b5a44_1006\n  - libgcc=7.2.0=h69d50b8_2\n  - libgcc-ng=9.1.0=hdf63c60_0\n  - libgfortran-ng=7.3.0=hdf63c60_0\n  - libiconv=1.15=h516909a_1005\n  - liblapack=3.8.0=10_openblas\n  - libnetcdf=4.6.2=h056eaf5_1002\n  - libopenblas=0.3.6=h6e990d7_4\n  - libpng=1.6.37=hed695b0_0\n  - libssh2=1.8.2=h22169c7_2\n  - libstdcxx-ng=9.1.0=hdf63c60_0\n  - libtiff=4.0.10=h57b8799_1003\n  - libuuid=2.32.1=h14c3975_1000\n  - libxcb=1.13=h14c3975_1002\n  - libxml2=2.9.9=h13577e0_1\n  - locket=0.2.0=py_2\n  - lz4-c=1.8.3=he1b5a44_1001\n  - markupsafe=1.1.1=py27h14c3975_0\n  - matplotlib=2.2.4=py27_0\n  - matplotlib-base=2.2.4=py27hfd891ef_0\n  - mpi=1.0=mpich\n  - mpich=3.2.1=hc99cbb1_1013\n  - msgpack-python=0.6.1=py27h6bb024c_0\n  - nbformat=4.4.0=py_1\n  - ncurses=6.1=hf484d3e_1002\n  - netcdf-fortran=4.4.5=hfc18c51_1001\n  - nettle=3.4.1=h1bed415_1002\n  - numpy=1.16.4=py27h95a1406_0\n  - olefile=0.46=py_0\n  - openblas=0.3.6=h6e990d7_4\n  - openh264=1.8.0=hdbcaa40_1000\n  - openssl=1.1.1c=h516909a_0\n  - output_viewer=1.2.6=py_0\n  - packaging=19.0=py_0\n  - pandas=0.24.2=py27hb3f55d8_0\n  - partd=1.0.0=py_0\n  - pcmdi_metrics=1.2.2019.07.18.19.25.g13d37ae=pyh39e3cac_0\n  - pcre=8.41=hf484d3e_1003\n  - pillow=6.1.0=py27he7afcd5_0\n  - pip=19.1.1=py27_0\n  - proj4=4.9.3=hc8507d1_7\n  - psutil=5.6.3=py27h516909a_0\n  - pthread-stubs=0.4=h14c3975_1001\n  - pycparser=2.19=py27_1\n  - pyopenssl=19.0.0=py27_0\n  - pyparsing=2.4.0=py_0\n  - pyqt=5.9.2=py27hcca6a23_0\n  - pyrsistent=0.15.3=py27h516909a_0\n  - pysocks=1.7.0=py27_0\n  - python=2.7.15=h5a48372_1009\n  - python-dateutil=2.8.0=py_0\n  - pytz=2019.1=py_0\n  - pyyaml=5.1.1=py27h516909a_0\n  - qt=5.9.7=h52cfd70_2\n  - readline=8.0=hf8c457e_0\n  - requests=2.22.0=py27_1\n  - setuptools=41.0.1=py27_0\n  - singledispatch=3.4.0.3=py27_1000\n  - sip=4.19.8=py27hf484d3e_1000\n  - six=1.12.0=py27_1000\n  - sortedcontainers=2.1.0=py_0\n  - sqlite=3.29.0=hcee41ef_0\n  - subprocess32=3.5.4=py27h516909a_0\n  - tblib=1.4.0=py_0\n  - tk=8.6.9=hed695b0_1002\n  - toolz=0.10.0=py_0\n  - tornado=5.1.1=py27h14c3975_1000\n  - traitlets=4.3.2=py27_1000\n  - udunits2=2.2.27.6=h4e0c4b3_1001\n  - urllib3=1.25.3=py27_0\n  - vcs=8.1.2019.07.11.14.20.gff404143=py_0\n  - vcsaddons=8.0.2019.07.09.20.59.g38002d6=py27h14c3975_0\n  - vtk-cdat=8.2.0.1916.8.0.2019.04.29.09.55.g5e9164e3da=py27h3df8362_0\n  - wheel=0.33.4=py27_0\n  - x264=1!152.20180806=h14c3975_0\n  - xorg-libxau=1.0.9=h14c3975_0\n  - xorg-libxdmcp=1.1.3=h516909a_0\n  - xz=5.2.4=h14c3975_1001\n  - yaml=0.1.7=h14c3975_1001\n  - zict=1.0.0=py_0\n  - zlib=1.2.11=h516909a_1005\n  - zstd=1.4.0=h3b9ef0a_0\n  - pip:\n    - cdms2==3.1.3\n    - regrid2==3.1.3\nprefix: /export_backup/gleckler1/anaconda3/envs/pmpn_0718\n\n",
    "References": {
        "default": {
            "MD5sum": "0b4c24d310f69c2518d6f8916cf25a06",
            "period": "198901-201002",
            "CMIP_CMOR_TABLE": "Amon",
            "RefName": "ERA-INT",
            "shape": "(12, 19, 121, 240)",
            "template": "/atmos/mon/ta/ERA-INT/gn/v20190221/ac/ta_mon_ERA-INT_BE_gn_198901-201002_AC.nc",
            "filename": "ta_mon_ERA-INT_BE_gn_198901-201002_AC.nc",
            "RefTrackingDate": "Fri Jul 12 13:07:03 2019"
        }
    },
    "RegionalMasking": {
        "TROPICS": {
            "domain": {
                "TROPICS": "cdutil.region.domain(latitude=(-30.0, 30))"
            },
            "id": "TROPICS"
        },
        "global": {
            "id": "global"
        },
        "NHEX": {
            "domain": {
                "NHEX": "cdutil.region.domain(latitude=(30.0, 90))"
            },
            "id": "NHEX"
        },
        "SHEX": {
            "domain": {
                "SHEX": "cdutil.region.domain(latitude=(-90.0, -30))"
            },
            "id": "SHEX"
        }
    },
    "Variable": {
        "id": "ta",
        "level": 20000.0
    },
    "DISCLAIMER": "USER-NOTICE: The results in this file were produced with the PMP v1.1 (https://github.com/PCMDI/pcmdi_metrics). They are for research purposes only. They are subject to ongoing quality control and change as the PMP software advances, interpolation methods are modified, observational data sets are updated, problems with model data are corrected, etc. Use of these results for research (presentation, publications, etc.) should reference: Gleckler, P. J., C. Doutriaux, P. J. Durack, K. E. Taylor, Y. Zhang, and D. N. Williams, E. Mason, and J. Servonnat (2016), A more powerful reality test for climate models, Eos, 97, doi:10.1029/2016EO051663. If any problems are uncovered in using these results please contact the PMP development team at pcmdi-metrics@llnl.gov\n",
    "GridInfo": {
        "GridResolution": [
            1,
            25,
            144
        ],
        "GridName": "2.5x2.5",
        "RegridMethod": "regrid2",
        "RegridTool": "regrid2"
    },
    "json_version": 3.0
}